spatial_casadi/__init__.py
spatial_casadi/spatial.py
spatial_casadi-1.1.0.dist-info/LICENSE
spatial_casadi-1.1.0.dist-info/METADATA
spatial_casadi-1.1.0.dist-info/WHEEL
spatial_casadi-1.1.0.dist-info/top_level.txt
spatial_casadi-1.1.0.dist-info/RECORD
