Metadata-Version: 2.1
Name: spatial-casadi
Version: 1.1.0
Summary: Spatial transformation library for CasADi Python. 
Home-page: https://github.com/cmower/spatial-casadi
Author: Christopher E. Mower
Author-email: "Christopher E. Mower" <christopher.mower@kcl.ac.uk>
License: LGPL-3.0 license
Project-URL: Homepage, https://cmower.github.io/spatial-casadi/
Project-URL: Documentation, https://cmower.github.io/spatial-casadi/
Project-URL: Bug Tracker, https://github.com/cmower/spatial-casadi/issues
Project-URL: Source, https://github.com/cmower/spatial-casadi
Classifier: Programming Language :: Python :: 3
Classifier: License :: OSI Approved :: GNU Lesser General Public License v3 or later (LGPLv3+)
Classifier: Operating System :: OS Independent
Requires-Python: >=3.7
License-File: LICENSE
Requires-Dist: casadi
Provides-Extra: test
Requires-Dist: pytest ; extra == 'test'
Requires-Dist: numpy ; extra == 'test'
Requires-Dist: scipy ; extra == 'test'
